passenv/__init__.py
passenv/completion.py
passenv/core.py
passenv/exporters.py
passenv/main.py
passenv/parser.py
passenv/pass_client.py
passenv-0.3.0.dist-info/METADATA
passenv-0.3.0.dist-info/WHEEL
passenv-0.3.0.dist-info/entry_points.txt
passenv-0.3.0.dist-info/licenses/LICENSE
passenv-0.3.0.dist-info/RECORD
